moviebox/__init__.py
moviebox/cli.py
moviebox/data.py
moviebox/main.py
moviebox/output.py
moviebox/recommender.py
moviebox/tfidf.py
moviebox/dataset/movies.csv
moviebox-0.3.0.dist-info/DESCRIPTION.rst
moviebox-0.3.0.dist-info/METADATA
moviebox-0.3.0.dist-info/RECORD
moviebox-0.3.0.dist-info/WHEEL
moviebox-0.3.0.dist-info/entry_points.txt
moviebox-0.3.0.dist-info/metadata.json
moviebox-0.3.0.dist-info/top_level.txt
