Metadata-Version: 2.0
Name: moviebox
Version: 0.3.0
Summary: Machine learning movie recommender
Home-page: https://github.com/klauscfhq/moviebox
Author: Klaus Sinani
Author-email: klauscfhq@protonmail.com
License: MIT
Platform: UNKNOWN
Classifier: Topic :: Software Development
Classifier: Topic :: Scientific/Engineering
Classifier: Programming Language :: Python
Classifier: Intended Audience :: Developers
Classifier: Intended Audience :: Science/Research
Classifier: Operating System :: OS Independent
Classifier: Programming Language :: Python :: 2
Classifier: Programming Language :: Python :: 2.7
Classifier: Programming Language :: Python :: 3
Classifier: Programming Language :: Python :: 3.4
Classifier: Programming Language :: Python :: 3.5
Classifier: Programming Language :: Python :: 3.6
Classifier: License :: OSI Approved :: MIT License
Requires-Python: >=2.7.*, !=3.0.*, !=3.1.*, !=3.2.*, !=3.3.*, <4
Requires-Dist: click
Requires-Dist: colorama
Requires-Dist: pandas
Requires-Dist: scikit-learn
Requires-Dist: termcolor
